canml/__init__.py
canml/canmlio.py
canmlio-0.1.0.dist-info/licenses/LICENSE
canmlio-0.1.0.dist-info/METADATA
canmlio-0.1.0.dist-info/WHEEL
canmlio-0.1.0.dist-info/top_level.txt
canmlio-0.1.0.dist-info/RECORD
