Metadata-Version: 2.4
Name: canmlio
Version: 0.1.0
Summary: Decode CAN BLF logs using DBC files into pandas DataFrames and export to CSV
Author-email: "Cosmin B. Memetea" <cosmin.memetea@gmail.com>
License: MIT
Requires-Python: >=3.8
License-File: LICENSE
Requires-Dist: cantools==39.4.4
Requires-Dist: python-can==4.4.0
Requires-Dist: pandas==2.2.2
Requires-Dist: numpy==1.26.4
Provides-Extra: test
Requires-Dist: pytest>=7.0.0; extra == "test"
Requires-Dist: coverage; extra == "test"
Requires-Dist: codecov; extra == "test"
Requires-Dist: twine; extra == "test"
Requires-Dist: build; extra == "test"
Dynamic: license-file
